synthaze/__init__.py
synthaze-0.1.dist-info/LICENSE
synthaze-0.1.dist-info/METADATA
synthaze-0.1.dist-info/WHEEL
synthaze-0.1.dist-info/top_level.txt
synthaze-0.1.dist-info/RECORD
