Metadata-Version: 2.1
Name: synthaze
Version: 0.1
Summary: Generate synthetic haze on images
Author: Suhith Nanayakkara
Author-email: suhith42@gmnail.com
License: UNKNOWN
Platform: UNKNOWN
Classifier: Programming Language :: Python :: 3
Classifier: License :: OSI Approved :: MIT License
Classifier: Operating System :: OS Independent
License-File: LICENSE
